{"results":[{"author":["johnalbin"],"keywords":["styleguide","kss","kss-node"],"description":["The Node.js port of KSS: A methodology for documenting CSS and building style guides"],"name":["kss"],"rating":[10],"homepage":["http://kss-node.github.io/kss-node"],"version":["3.0.0-beta.14"],"modified":["2016-05-23T11:26:07.187Z"]},{"author":["tjholowaychuk"],"description":["Stylus mixins and utilities"],"name":["nib"],"rating":[10],"homepage":["https://github.com/visionmedia/nib#readme"],"version":["1.1.2"],"modified":["2016-08-05T17:59:50.497Z"]},{"author":["goatslacker"],"keywords":["alt","es6","flow","flux","react","unidirectional"],"description":["A flux implementation"],"name":["alt"],"rating":[10],"homepage":["https://github.com/goatslacker/alt"],"version":["0.18.5"],"modified":["2016-07-17T18:38:17.056Z"]},{"author":["koistya"],"keywords":["gulpplugin","css","csscomb","lint","linter","preprocessor"],"description":["CSScomb is a coding style formatter for CSS."],"name":["gulp-csscomb"],"rating":[10],"homepage":["http://github.com/koistya/gulp-csscomb"],"version":["3.0.7"],"modified":["2016-03-21T12:26:42.097Z"]},{"author":["mattdesl"],"keywords":["browserify","watchify","browser","dev","development","server","beefy","wzrd","local","locally","localhost","watch","live","reload","livereload","lr"],"description":["a browserify server for rapid prototyping"],"name":["budo"],"rating":[10],"homepage":["https://github.com/mattdesl/budo"],"version":["9.0.0"],"modified":["2016-08-16T00:18:20.158Z"]},{"author":["lazd"],"keywords":["csslint","gulpplugin"],"description":["CSSLint plugin for gulp"],"name":["gulp-csslint"],"rating":[10],"homepage":["https://github.com/lazd/gulp-csslint#readme"],"version":["1.0.0"],"modified":["2016-08-20T20:24:56.509Z"]},{"author":["nicks"],"keywords":["phantomjs","headless","webkit"],"description":["Headless WebKit with JS API"],"name":["phantomjs-prebuilt"],"rating":[10],"homepage":["https://github.com/Medium/phantomjs"],"version":["2.1.12"],"modified":["2016-08-12T12:42:45.577Z"]},{"author":["tschaub"],"keywords":["files","grunt","gruntplugin","newer"],"description":["Run Grunt tasks with only those source files modified since the last successful run."],"name":["grunt-newer"],"rating":[10],"homepage":["https://github.com/tschaub/grunt-newer"],"version":["1.2.0"],"modified":["2016-04-13T15:20:03.320Z"]},{"author":["vladikoff"],"keywords":["gruntplugin"],"description":["Optimize RequireJS projects using r.js"],"name":["grunt-contrib-requirejs"],"rating":[10],"homepage":["https://github.com/gruntjs/grunt-contrib-requirejs#readme"],"version":["1.0.0"],"modified":["2016-03-04T21:14:13.990Z"]},{"author":["woodyrew"],"keywords":["static","file","site","website","blog","generator","markdown","jekyll","wintersmith","blacksmith"],"description":["An extremely simple, pluggable static site generator."],"name":["metalsmith"],"rating":[10],"homepage":["https://github.com/segmentio/metalsmith#readme"],"version":["2.2.0"],"modified":["2016-08-15T18:35:12.377Z"]},{"author":["sindresorhus"],"keywords":["grunt","tasks","measure","time","profile","stat","stats","perf","performance","tasks"],"description":["Display the elapsed execution time of grunt tasks"],"name":["time-grunt"],"rating":[10],"homepage":["https://github.com/sindresorhus/time-grunt#readme"],"version":["1.4.0"],"modified":["2016-07-20T13:28:58.801Z"]},{"author":["twokul"],"keywords":["ember.js","ember","cli","app","kit","app-kit","ember-app-kit"],"description":["Command line tool for developing ambitious ember.js apps"],"name":["ember-cli"],"rating":[10],"homepage":["http://ember-cli.com/"],"version":["2.7.0"],"modified":["2016-07-26T06:15:58.938Z"]},{"author":["sindresorhus"],"keywords":["gulpplugin","strip","remove","delete","clean","debug","debugger","console","log","logging","js","javascript","ecmascript","ast","esprima"],"description":["Strip console and debugger statements from JavaScript code"],"name":["gulp-strip-debug"],"rating":[10],"homepage":["https://github.com/sindresorhus/gulp-strip-debug"],"version":["1.1.0"],"modified":["2015-11-14T13:27:22.069Z"]},{"author":["shama"],"keywords":["gruntplugin","watch","livereload"],"description":["Run predefined tasks whenever watched file patterns are added, changed or deleted"],"name":["grunt-contrib-watch"],"rating":[10],"homepage":["https://github.com/gruntjs/grunt-contrib-watch"],"version":["1.0.0"],"modified":["2016-03-12T22:09:43.947Z"]},{"author":["phated"],"keywords":["build","stream","system","make","tool","asset","pipeline"],"description":["The streaming build system"],"name":["gulp"],"rating":[10],"homepage":["http://gulpjs.com/"],"version":["3.9.1"],"modified":["2016-04-08T19:17:57.830Z"]},{"author":["medikoo"],"keywords":["memoize","memoizer","cache","memoization","memo","memcached","hashing.","storage","caching","memory","gc","weak","garbage","collector","async"],"description":["Memoize/cache function results"],"name":["memoizee"],"rating":[10],"homepage":["https://github.com/medikoo/memoizee#readme"],"version":["0.4.1"],"modified":["2016-07-13T08:06:54.682Z"]},{"author":["gaearon"],"keywords":["babel-plugin","react-transform","instrumentation","dx","react","reactjs","components"],"description":["Babel plugin to instrument React components with custom transforms"],"name":["babel-plugin-react-transform"],"rating":[10],"homepage":["https://github.com/gaearon/babel-plugin-react-transform#readme"],"version":["2.0.2"],"modified":["2016-03-05T01:31:11.804Z"]},{"author":["stevelacy"],"keywords":["gulp","stylus","css","preprocessor","gulpplugin","gulp-plugin"],"description":["Stylus plugin for gulp"],"name":["gulp-stylus"],"rating":[10],"homepage":["http://github.com/stevelacy/gulp-stylus"],"version":["2.5.0"],"modified":["2016-06-21T18:56:17.959Z"]},{"author":["shootaroo"],"keywords":["grunt","gruntplugin","jit","loader"],"description":["JIT plugin loader for Grunt."],"name":["jit-grunt"],"rating":[10],"homepage":["https://github.com/shootaroo/jit-grunt"],"version":["0.10.0"],"modified":["2016-02-23T14:31:34.815Z"]},{"author":["sindresorhus"],"keywords":["gruntplugin","babel","transpiler","es2015","es6","rewriting","transformation","syntax","codegen","desugaring","javascript","ecmascript","compiler"],"description":["Use next generation JavaScript, today"],"name":["grunt-babel"],"rating":[10],"homepage":["https://github.com/babel/grunt-babel"],"version":["6.0.0"],"modified":["2015-10-30T06:22:34.674Z"]}],"total":49521,"size":"20","from":"0"}